zuss/__init__.py
zuss/cmd.py
zuss/usbswsdk.py
zuss/usbswsdk_unittest.py
zuss-2.1.1.dist-info/METADATA
zuss-2.1.1.dist-info/WHEEL
zuss-2.1.1.dist-info/top_level.txt
zuss-2.1.1.dist-info/RECORD
