Metadata-Version: 2.1
Name: zuss
Version: 2.1.1
Summary: ZD USB Shifter SDK
Home-page: https://github.com/Klareliebe7/zuss
Author: zhengkunli
Author-email: 1st.melchior@gmail.com
License: MIT
Platform: UNKNOWN
Classifier: Programming Language :: Python :: 3
Classifier: License :: OSI Approved :: MIT License
Classifier: Operating System :: OS Independent
Requires-Python: >=3.8.0
Requires-Dist: serial
Requires-Dist: argparse
Requires-Dist: colorama
